lex_game-0.1.11.dist-info/licenses/LICENSE
lexcel/__init__.py
lexcel/game.py
lexcel/lex.py
lexcel/lexcel.py
lexcel/py.typed
lexweb/__init__.py
lexweb/app.py
lexweb/static/css/style.css
lexweb/static/js/game.js
lexweb/templates/index.html
lex_game-0.1.11.dist-info/METADATA
lex_game-0.1.11.dist-info/WHEEL
lex_game-0.1.11.dist-info/entry_points.txt
lex_game-0.1.11.dist-info/top_level.txt
lex_game-0.1.11.dist-info/RECORD
