Metadata-Version: 2.4
Name: lex_game
Version: 0.1.11
Summary: LEX is Martin Gardner's Hexapawn where matchboxes are Excel files
Author-email: Mattia Monga <mattia.monga@unimi.it>
License: GPL-3.0-or-later
Project-URL: Homepage, https://gitlab.com/mmonga/lex
Classifier: Programming Language :: Python :: 3
Classifier: Operating System :: OS Independent
Classifier: Topic :: Games/Entertainment :: Board Games
Requires-Python: >=3.10
License-File: LICENSE
Requires-Dist: openpyxl
Provides-Extra: web
Requires-Dist: flask; extra == "web"
Dynamic: license-file
